kurek/__init__.py
kurek/__main__.py
kurek/ajax.py
kurek/config.py
kurek/downloaders.py
kurek/http.py
kurek/json.py
kurek/utils.py
kurek-0.2.1.dist-info/LICENSE.md
kurek-0.2.1.dist-info/METADATA
kurek-0.2.1.dist-info/WHEEL
kurek-0.2.1.dist-info/entry_points.txt
kurek-0.2.1.dist-info/top_level.txt
kurek-0.2.1.dist-info/RECORD
