Metadata-Version: 2.1
Name: kurek
Version: 0.2.1
Summary: Download photos and videos from zbiornik.com
Author-email: Bartosz Bartyzel <barnxba@gmail.com>
License: MIT License        
Project-URL: Homepage, https://github.com/barnxba/kurek
Keywords: kurek,zbiornik,zbiornik.com
Classifier: License :: OSI Approved :: MIT License
Classifier: Programming Language :: Python
Classifier: Programming Language :: Python :: 3
Requires-Python: >=3.8
License-File: LICENSE.md
Requires-Dist: aiofiles (>=0.8.0)
Requires-Dist: aiohttp (>=3.8.1)
Requires-Dist: beautifulsoup4 (>=4.11.1)
Requires-Dist: yarl (>=1.7.2)
Requires-Dist: tqdm (>=4.64.0)
